oass/AlgorithmicTrading.py
oass/GradientCalculator.py
oass/ShortestPath.py
oass/StaticDirectedAcyclicGraph.py
oass/__init__.py
oass-1.0.0.dist-info/METADATA
oass-1.0.0.dist-info/WHEEL
oass-1.0.0.dist-info/top_level.txt
oass-1.0.0.dist-info/RECORD
