Metadata-Version: 2.1
Name: oass
Version: 1.0.0
Summary: Optimal Action Space Search (OASS) is an algorithm for path planning problems on directed acyclic graphs (DAG) based on reinforcement learning (RL) theory.
Home-page: https://github.com/ECNU-CILAB/OASS
Author: Artiprocher
Author-email: zjduan@stu.ecnu.edu.cn
License: UNKNOWN
Platform: UNKNOWN
